{
    "$schema": "https://schema.management.azure.com/schemas/2015-01-01/deploymentParameters.json#",
    "contentVersion": "1.0.0.0",
    "parameters": {
        "omsRecoveryVaultName": {
            "value": "QuickStartOMSVault"
        },
        "omsRecoveryVaultRegion": {
            "value": "EastUS"
        },
        "omsWorkspaceName": {
            "value": "QuickStartOMS"
        },
        "omsWorkspaceRegion": {
            "value": "EastUS"
        },
        "omsAutomationAccountName": {
            "value": "QuickStartOMSAutomation"
        },
        "omsAutomationRegion": {
            "value": "USEast    "
        },
        "azureAdminPwd": {
            "value": "GEN-PASSWORD"
        },
        "azureAdmin": {
            "value": "azureadmin"
        },
        "_artifactsLocation": {
            "value": "https://raw.githubusercontent.com/lagimik/azure-quickstart-templates/master/oms-all-deploy"
        }
    }
}